MANIFEST.in
README.rst
setup.py
aliyun_python_sdk_aas_test.egg-info/PKG-INFO
aliyun_python_sdk_aas_test.egg-info/SOURCES.txt
aliyun_python_sdk_aas_test.egg-info/dependency_links.txt
aliyun_python_sdk_aas_test.egg-info/requires.txt
aliyun_python_sdk_aas_test.egg-info/top_level.txt
aliyunsdkaas/__init__.py
aliyunsdkaas/request/__init__.py
aliyunsdkaas/request/v20150701/CreateAccessKeyForAccountRequest.py
aliyunsdkaas/request/v20150701/CreateAliyunAccountRequest.py
aliyunsdkaas/request/v20150701/DeleteAccessKeyForAccountRequest.py
aliyunsdkaas/request/v20150701/GetBasicInfoForAccountRequest.py
aliyunsdkaas/request/v20150701/ListAccessKeysForAccountRequest.py
aliyunsdkaas/request/v20150701/UpdateAccessKeyStatusForAccountRequest.py
aliyunsdkaas/request/v20150701/UpdatePasswordForAccountRequest.py
aliyunsdkaas/request/v20150701/__init__.py